com/__init__.py
com/yootk/__init__.py
com/yootk/data.py
com/yootk/message.py
yootk_com-0.0.1.dist-info/METADATA
yootk_com-0.0.1.dist-info/WHEEL
yootk_com-0.0.1.dist-info/top_level.txt
yootk_com-0.0.1.dist-info/RECORD
